Workbook

Sheet Cover
B3: PROJECT OSPREY
B5: Rolls-Royce Holdings plc | LSE: RR.
B9: Deal Code: | C9: Project Osprey
B10: Target: | C10: Rolls-Royce Holdings plc
B11: Ticker: | C11: LSE: RR.
B12: Sector: | C12: Aerospace, Defence & Power Systems
B13: Headquarters: | C13: London, United Kingdom
B14: Date of Analysis: | C14: 23 May 2026
B15: Prepared by: | C15: M&A Advisory — Senior VP
B16: Status: | C16: DRAFT — IC Pre-read
B19: WORKBOOK MAP
B21: Tab | C21: Purpose
B22: Cover | C22: Project identification, workbook map, disclaimer
B23: Assumptions | C23: Hardcoded inputs: WACC build, growth, terminal, share count
B24: DCF | C24: 5-yr FCF projection, terminal value, equity bridge, 2-way data table
B27: FORMATTING CONVENTIONS
B29: Blue | C29: Hardcoded inputs / assumptions
B30: Black | C30: Formula / calculation
B31: Green | C31: Cross-sheet link within workbook
B32: Yellow fill | C32: Key assumption requiring committee attention
B35: DISCLAIMER
B37: Prepared for internal Investment Committee use only. Figures sourced from RR Holdings plc FY2025 Results (26-Feb-2026). Not for external distribution.

Sheet Assumptions
B2: ASSUMPTIONS
B3: All figures £bn unless stated. Source: RR FY25 results, 26-Feb-2026.
B5: Fiscal Year | C5: 2025A | D5: 2026E | E5: 2027E | F5: 2028E | G5: 2029E | H5: 2030E | I5: Source / Note
B7: OPERATING ASSUMPTIONS
B8: Underlying Operating Profit (£bn) | C8: 3.46 | D8: 4.1 | E8: 4.55 | F8: 5.05 | G8: 5.4 | H8: 5.7 | I8: FY25 actual; FY26/28 mgmt mid-pt; FY27/29/30 interpolated
B9: Underlying Operating Margin | C9: 0.173 | D9: 0.18 | E9: 0.188 | F9: 0.195 | G9: 0.2 | H9: 0.205 | I9: Margin walk: 17.3% → 20.5% across forecast
B10: Implied Revenue (£bn) | C10: =C8/C9 -> 20 | D10: =D8/D9 -> 22.777778 | E10: =E8/E9 -> 24.202128 | F10: =F8/F9 -> 25.897436 | G10: =G8/G9 -> 27 | H10: =H8/H9 -> 27.804878 | I10: Profit / margin
B12: FREE CASH FLOW BUILD
B13: Free Cash Flow (£bn) | C13: 3.3 | D13: 3.7 | E13: 4.4 | F13: 5.15 | G13: 5.45 | H13: 5.7 | I13: FY25 actual £3.3bn; FY26 £3.6-3.8bn mid; FY28 £5.0-5.3bn mid
B14: FCF YoY Growth | C14: n/a | D14: =D13/C13-1 -> 0.12121212 | E14: =E13/D13-1 -> 0.18918919 | F14: =F13/E13-1 -> 0.17045455 | G14: =G13/F13-1 -> 0.058252427 | H14: =H13/G13-1 -> 0.04587156 | I14: Reflects engine LLP flywheel ramp
B15: FCF / Underlying Op Profit | C15: =C13/C8 -> 0.95375723 | D15: =D13/D8 -> 0.90243902 | E15: =E13/E8 -> 0.96703297 | F15: =F13/F8 -> 1.019802 | G15: =G13/G8 -> 1.0092593 | H15: =H13/H8 -> 1 | I15: Cash conversion proxy
B17: WACC BUILD
B18: Risk-free rate (UK 10Y Gilt) | C18: 0.045 | I18: Bloomberg, May-26
B19: Equity risk premium | C19: 0.05 | I19: Damodaran mature equity
B20: Levered beta | C20: 1.1 | I20: 5Y wkly vs FTSE100
B21: Cost of equity | C21: =C18+C19*C20 -> 0.1 | I21: Rf + β × ERP
B22: Pre-tax cost of debt | C22: 0.05 | I22: RR senior notes 2034
B23: Tax rate | C23: 0.25 | I23: UK statutory
B24: After-tax cost of debt | C24: =C22*(1-C23) -> 0.0375 | I24: Kd × (1-t)
B25: Equity weight | C25: 0.92 | I25: Target capital structure
B26: Debt weight | C26: 0.08 | I26: 1-equity weight
B27: WACC | C27: =C21*C25+C24*C26 -> 0.095 | I27: BASE CASE
B29: TERMINAL & EQUITY ASSUMPTIONS
B30: Terminal growth rate (g) | C30: 0.0225 | I30: Long-run UK CPI + real growth
B31: Shares outstanding (bn) | C31: 8.3 | I31: Market cap £100bn / £12.08
B32: Net cash position (£bn) | C32: 1.9 | I32: 31-Dec-2025
B33: Current share price (p) | C33: 1208.2 | I33: LSE close 21-May-26
B34: Valuation date | C34: 23-May-2026 | I34: Today
B36: CAPITAL RETURN PROGRAM
B37: Total Buyback Authorisation (£bn) | C37: 8 | I37: Mid-pt of £7-9bn (2026-28)
B38: Initial Tranche 2026 (£bn) | C38: 2.5 | I38: Announced Feb-26

Sheet DCF
B2: DCF VALUATION — RR HOLDINGS
B3: All figures £bn unless stated. | Valuation date: 23-May-2026
B5: (£bn) | C5: 2025A | D5: 2026E | E5: 2027E | F5: 2028E | G5: 2029E | H5: 2030E | I5: Terminal
B7: FREE CASH FLOW PROJECTION
B8: Underlying Operating Profit | C8: =Assumptions!C8 -> 3.46 | D8: =Assumptions!D8 -> 4.1 | E8: =Assumptions!E8 -> 4.55 | F8: =Assumptions!F8 -> 5.05 | G8: =Assumptions!G8 -> 5.4 | H8: =Assumptions!H8 -> 5.7
B9: Free Cash Flow | C9: =Assumptions!C13 -> 3.3 | D9: =Assumptions!D13 -> 3.7 | E9: =Assumptions!E13 -> 4.4 | F9: =Assumptions!F13 -> 5.15 | G9: =Assumptions!G13 -> 5.45 | H9: =Assumptions!H13 -> 5.7
B10: YoY Growth % | C10: n/a | D10: =D9/C9-1 -> 0.12121212 | E10: =E9/D9-1 -> 0.18918919 | F10: =F9/E9-1 -> 0.17045455 | G10: =G9/F9-1 -> 0.058252427 | H10: =H9/G9-1 -> 0.04587156
B11: Bridge to 2028 target (cum.) | F11: =F9-C9 -> 1.85
B13: DCF MECHANICS
B14: WACC (base case) | C14: =Assumptions!C27 -> 0.095
B15: Terminal growth rate (g) | C15: =Assumptions!C30 -> 0.0225
B17: Discount Period (mid-year convention) | D17: 0.6 | E17: 1.5 | F17: 2.5 | G17: 3.5 | H17: 4.5 | I17: 4.5
B18: Discount Factor | D18: =1/(1+$C$14)^D17 -> 0.94700338 | E18: =1/(1+$C$14)^E17 -> 0.87272782 | F18: =1/(1+$C$14)^F17 -> 0.79701171 | G18: =1/(1+$C$14)^G17 -> 0.72786458 | H18: =1/(1+$C$14)^H17 -> 0.66471651 | I18: =1/(1+$C$14)^I17 -> 0.66471651
B20: Terminal Value (Gordon Growth) | I20: =H9*(1+$C$15)/($C$14-$C$15) -> 80.389655
B22: Cash Flow for Discounting | D22: =D9 -> 3.7 | E22: =E9 -> 4.4 | F22: =F9 -> 5.15 | G22: =G9 -> 5.45 | H22: =H9 -> 5.7 | I22: =I20 -> 80.389655
B23: PV of Cash Flow | D23: =D22*D18 -> 3.5039125 | E23: =E22*E18 -> 3.8400024 | F23: =F22*F18 -> 4.1046103 | G23: =G22*G18 -> 3.9668619 | H23: =H22*H18 -> 3.7888841 | I23: =I22*I18 -> 53.436331
B26: VALUATION BRIDGE
B28: Sum of PV of explicit forecast (2026-30) | C28: =SUM(D23:H23) -> 19.204271
B29: PV of Terminal Value | C29: =I23 -> 53.436331
B30: Enterprise Value | C30: =C28+C29 -> 72.640602
B31: (+) Net Cash | C31: =Assumptions!C32 -> 1.9
B32: Equity Value | C32: =C30+C31 -> 74.540602
B33: Shares Outstanding (bn) | C33: =Assumptions!C31 -> 8.3
B34: Implied Share Price (£) | C34: =C32/C33 -> 8.9807954
B35: Current Share Price (£) | C35: =Assumptions!C33/100 -> 12.082
B36: Implied Upside / (Downside) | C36: =C34/C35-1 -> -0.25667974
B39: SENSITIVITY: IMPLIED SHARE PRICE (£) — WACC vs TERMINAL GROWTH
B40: Rows: WACC | Columns: Terminal growth rate (g)
C42: g → | D42: 0.015 | E42: 0.018 | F42: 0.02 | G42: 0.0225 | H42: 0.025 | I42: 0.0275 | J42: 0.03
C43: 0.08 | D43: =($D$9/(1+$C43)^0.6+$E$9/(1+$C43)^1.5+$F$9/(1+$C43)^2.5+$G$9/(1+$C43)^3.5+$H$9/(1+$C43)^4.5+($H$9*(1+D$42)/($C43-D$42))/(1+$C43)^4.5+Assumptions!$C$32)/Assumptions!$C$31 -> 10.210858 | E43: =($D$9/(1+$C43)^0.6+$E$9/(1+$C43)^1.5+$F$9/(1+$C43)^2.5+$G$9/(1+$C43)^3.5+$H$9/(1+$C43)^4.5+($H$9*(1+E$42)/($C43-E$42))/(1+$C43)^4.5+Assumptions!$C$32)/Assumptions!$C$31 -> 10.601366 | F43: =($D$9/(1+$C43)^0.6+$E$9/(1+$C43)^1.5+$F$9/(1+$C43)^2.5+$G$9/(1+$C43)^3.5+$H$9/(1+$C43)^4.5+($H$9*(1+F$42)/($C43-F$42))/(1+$C43)^4.5+Assumptions!$C$32)/Assumptions!$C$31 -> 10.883399 | G43: =($D$9/(1+$C43)^0.6+$E$9/(1+$C43)^1.5+$F$9/(1+$C43)^2.5+$G$9/(1+$C43)^3.5+$H$9/(1+$C43)^4.5+($H$9*(1+G$42)/($C43-G$42))/(1+$C43)^4.5+Assumptions!$C$32)/Assumptions!$C$31 -> 11.263531 | H43: =($D$9/(1+$C43)^0.6+$E$9/(1+$C43)^1.5+$F$9/(1+$C43)^2.5+$G$9/(1+$C43)^3.5+$H$9/(1+$C43)^4.5+($H$9*(1+H$42)/($C43-H$42))/(1+$C43)^4.5+Assumptions!$C$32)/Assumptions!$C$31 -> 11.678221 | I43: =($D$9/(1+$C43)^0.6+$E$9/(1+$C43)^1.5+$F$9/(1+$C43)^2.5+$G$9/(1+$C43)^3.5+$H$9/(1+$C43)^4.5+($H$9*(1+I$42)/($C43-I$42))/(1+$C43)^4.5+Assumptions!$C$32)/Assumptions!$C$31 -> 12.132405 | J43: =($D$9/(1+$C43)^0.6+$E$9/(1+$C43)^1.5+$F$9/(1+$C43)^2.5+$G$9/(1+$C43)^3.5+$H$9/(1+$C43)^4.5+($H$9*(1+J$42)/($C43-J$42))/(1+$C43)^4.5+Assumptions!$C$32)/Assumptions!$C$31 -> 12.632007
C44: 0.085 | D44: =($D$9/(1+$C44)^0.6+$E$9/(1+$C44)^1.5+$F$9/(1+$C44)^2.5+$G$9/(1+$C44)^3.5+$H$9/(1+$C44)^4.5+($H$9*(1+D$42)/($C44-D$42))/(1+$C44)^4.5+Assumptions!$C$32)/Assumptions!$C$31 -> 9.4958574 | E44: =($D$9/(1+$C44)^0.6+$E$9/(1+$C44)^1.5+$F$9/(1+$C44)^2.5+$G$9/(1+$C44)^3.5+$H$9/(1+$C44)^4.5+($H$9*(1+E$42)/($C44-E$42))/(1+$C44)^4.5+Assumptions!$C$32)/Assumptions!$C$31 -> 9.82603 | F44: =($D$9/(1+$C44)^0.6+$E$9/(1+$C44)^1.5+$F$9/(1+$C44)^2.5+$G$9/(1+$C44)^3.5+$H$9/(1+$C44)^4.5+($H$9*(1+F$42)/($C44-F$42))/(1+$C44)^4.5+Assumptions!$C$32)/Assumptions!$C$31 -> 10.063077 | G44: =($D$9/(1+$C44)^0.6+$E$9/(1+$C44)^1.5+$F$9/(1+$C44)^2.5+$G$9/(1+$C44)^3.5+$H$9/(1+$C44)^4.5+($H$9*(1+G$42)/($C44-G$42))/(1+$C44)^4.5+Assumptions!$C$32)/Assumptions!$C$31 -> 10.38072 | H44: =($D$9/(1+$C44)^0.6+$E$9/(1+$C44)^1.5+$F$9/(1+$C44)^2.5+$G$9/(1+$C44)^3.5+$H$9/(1+$C44)^4.5+($H$9*(1+H$42)/($C44-H$42))/(1+$C44)^4.5+Assumptions!$C$32)/Assumptions!$C$31 -> 10.724833 | I44: =($D$9/(1+$C44)^0.6+$E$9/(1+$C44)^1.5+$F$9/(1+$C44)^2.5+$G$9/(1+$C44)^3.5+$H$9/(1+$C44)^4.5+($H$9*(1+I$42)/($C44-I$42))/(1+$C44)^4.5+Assumptions!$C$32)/Assumptions!$C$31 -> 11.098869 | J44: =($D$9/(1+$C44)^0.6+$E$9/(1+$C44)^1.5+$F$9/(1+$C44)^2.5+$G$9/(1+$C44)^3.5+$H$9/(1+$C44)^4.5+($H$9*(1+J$42)/($C44-J$42))/(1+$C44)^4.5+Assumptions!$C$32)/Assumptions!$C$31 -> 11.506909
C45: 0.09 | D45: =($D$9/(1+$C45)^0.6+$E$9/(1+$C45)^1.5+$F$9/(1+$C45)^2.5+$G$9/(1+$C45)^3.5+$H$9/(1+$C45)^4.5+($H$9*(1+D$42)/($C45-D$42))/(1+$C45)^4.5+Assumptions!$C$32)/Assumptions!$C$31 -> 8.8763496 | E45: =($D$9/(1+$C45)^0.6+$E$9/(1+$C45)^1.5+$F$9/(1+$C45)^2.5+$G$9/(1+$C45)^3.5+$H$9/(1+$C45)^4.5+($H$9*(1+E$42)/($C45-E$42))/(1+$C45)^4.5+Assumptions!$C$32)/Assumptions!$C$31 -> 9.1585331 | F45: =($D$9/(1+$C45)^0.6+$E$9/(1+$C45)^1.5+$F$9/(1+$C45)^2.5+$G$9/(1+$C45)^3.5+$H$9/(1+$C45)^4.5+($H$9*(1+F$42)/($C45-F$42))/(1+$C45)^4.5+Assumptions!$C$32)/Assumptions!$C$31 -> 9.3600927 | G45: =($D$9/(1+$C45)^0.6+$E$9/(1+$C45)^1.5+$F$9/(1+$C45)^2.5+$G$9/(1+$C45)^3.5+$H$9/(1+$C45)^4.5+($H$9*(1+G$42)/($C45-G$42))/(1+$C45)^4.5+Assumptions!$C$32)/Assumptions!$C$31 -> 9.6288388 | H45: =($D$9/(1+$C45)^0.6+$E$9/(1+$C45)^1.5+$F$9/(1+$C45)^2.5+$G$9/(1+$C45)^3.5+$H$9/(1+$C45)^4.5+($H$9*(1+H$42)/($C45-H$42))/(1+$C45)^4.5+Assumptions!$C$32)/Assumptions!$C$31 -> 9.9182577 | I45: =($D$9/(1+$C45)^0.6+$E$9/(1+$C45)^1.5+$F$9/(1+$C45)^2.5+$G$9/(1+$C45)^3.5+$H$9/(1+$C45)^4.5+($H$9*(1+I$42)/($C45-I$42))/(1+$C45)^4.5+Assumptions!$C$32)/Assumptions!$C$31 -> 10.23083 | J45: =($D$9/(1+$C45)^0.6+$E$9/(1+$C45)^1.5+$F$9/(1+$C45)^2.5+$G$9/(1+$C45)^3.5+$H$9/(1+$C45)^4.5+($H$9*(1+J$42)/($C45-J$42))/(1+$C45)^4.5+Assumptions!$C$32)/Assumptions!$C$31 -> 10.56945
C46: 0.095 | D46: =($D$9/(1+$C46)^0.6+$E$9/(1+$C46)^1.5+$F$9/(1+$C46)^2.5+$G$9/(1+$C46)^3.5+$H$9/(1+$C46)^4.5+($H$9*(1+D$42)/($C46-D$42))/(1+$C46)^4.5+Assumptions!$C$32)/Assumptions!$C$31 -> 8.3344263 | E46: =($D$9/(1+$C46)^0.6+$E$9/(1+$C46)^1.5+$F$9/(1+$C46)^2.5+$G$9/(1+$C46)^3.5+$H$9/(1+$C46)^4.5+($H$9*(1+E$42)/($C46-E$42))/(1+$C46)^4.5+Assumptions!$C$32)/Assumptions!$C$31 -> 8.577864 | F46: =($D$9/(1+$C46)^0.6+$E$9/(1+$C46)^1.5+$F$9/(1+$C46)^2.5+$G$9/(1+$C46)^3.5+$H$9/(1+$C46)^4.5+($H$9*(1+F$42)/($C46-F$42))/(1+$C46)^4.5+Assumptions!$C$32)/Assumptions!$C$31 -> 8.7509753 | G46: =($D$9/(1+$C46)^0.6+$E$9/(1+$C46)^1.5+$F$9/(1+$C46)^2.5+$G$9/(1+$C46)^3.5+$H$9/(1+$C46)^4.5+($H$9*(1+G$42)/($C46-G$42))/(1+$C46)^4.5+Assumptions!$C$32)/Assumptions!$C$31 -> 8.9807954 | H46: =($D$9/(1+$C46)^0.6+$E$9/(1+$C46)^1.5+$F$9/(1+$C46)^2.5+$G$9/(1+$C46)^3.5+$H$9/(1+$C46)^4.5+($H$9*(1+H$42)/($C46-H$42))/(1+$C46)^4.5+Assumptions!$C$32)/Assumptions!$C$31 -> 9.2270313 | I46: =($D$9/(1+$C46)^0.6+$E$9/(1+$C46)^1.5+$F$9/(1+$C46)^2.5+$G$9/(1+$C46)^3.5+$H$9/(1+$C46)^4.5+($H$9*(1+I$42)/($C46-I$42))/(1+$C46)^4.5+Assumptions!$C$32)/Assumptions!$C$31 -> 9.4915068 | J46: =($D$9/(1+$C46)^0.6+$E$9/(1+$C46)^1.5+$F$9/(1+$C46)^2.5+$G$9/(1+$C46)^3.5+$H$9/(1+$C46)^4.5+($H$9*(1+J$42)/($C46-J$42))/(1+$C46)^4.5+Assumptions!$C$32)/Assumptions!$C$31 -> 9.7763267
C47: 0.1 | D47: =($D$9/(1+$C47)^0.6+$E$9/(1+$C47)^1.5+$F$9/(1+$C47)^2.5+$G$9/(1+$C47)^3.5+$H$9/(1+$C47)^4.5+($H$9*(1+D$42)/($C47-D$42))/(1+$C47)^4.5+Assumptions!$C$32)/Assumptions!$C$31 -> 7.8563928 | E47: =($D$9/(1+$C47)^0.6+$E$9/(1+$C47)^1.5+$F$9/(1+$C47)^2.5+$G$9/(1+$C47)^3.5+$H$9/(1+$C47)^4.5+($H$9*(1+E$42)/($C47-E$42))/(1+$C47)^4.5+Assumptions!$C$32)/Assumptions!$C$31 -> 8.0681366 | F47: =($D$9/(1+$C47)^0.6+$E$9/(1+$C47)^1.5+$F$9/(1+$C47)^2.5+$G$9/(1+$C47)^3.5+$H$9/(1+$C47)^4.5+($H$9*(1+F$42)/($C47-F$42))/(1+$C47)^4.5+Assumptions!$C$32)/Assumptions!$C$31 -> 8.2181219 | G47: =($D$9/(1+$C47)^0.6+$E$9/(1+$C47)^1.5+$F$9/(1+$C47)^2.5+$G$9/(1+$C47)^3.5+$H$9/(1+$C47)^4.5+($H$9*(1+G$42)/($C47-G$42))/(1+$C47)^4.5+Assumptions!$C$32)/Assumptions!$C$31 -> 8.4164894 | H47: =($D$9/(1+$C47)^0.6+$E$9/(1+$C47)^1.5+$F$9/(1+$C47)^2.5+$G$9/(1+$C47)^3.5+$H$9/(1+$C47)^4.5+($H$9*(1+H$42)/($C47-H$42))/(1+$C47)^4.5+Assumptions!$C$32)/Assumptions!$C$31 -> 8.6280815 | I47: =($D$9/(1+$C47)^0.6+$E$9/(1+$C47)^1.5+$F$9/(1+$C47)^2.5+$G$9/(1+$C47)^3.5+$H$9/(1+$C47)^4.5+($H$9*(1+I$42)/($C47-I$42))/(1+$C47)^4.5+Assumptions!$C$32)/Assumptions!$C$31 -> 8.8542662 | J47: =($D$9/(1+$C47)^0.6+$E$9/(1+$C47)^1.5+$F$9/(1+$C47)^2.5+$G$9/(1+$C47)^3.5+$H$9/(1+$C47)^4.5+($H$9*(1+J$42)/($C47-J$42))/(1+$C47)^4.5+Assumptions!$C$32)/Assumptions!$C$31 -> 9.0966068
C48: 0.105 | D48: =($D$9/(1+$C48)^0.6+$E$9/(1+$C48)^1.5+$F$9/(1+$C48)^2.5+$G$9/(1+$C48)^3.5+$H$9/(1+$C48)^4.5+($H$9*(1+D$42)/($C48-D$42))/(1+$C48)^4.5+Assumptions!$C$32)/Assumptions!$C$31 -> 7.4315979 | E48: =($D$9/(1+$C48)^0.6+$E$9/(1+$C48)^1.5+$F$9/(1+$C48)^2.5+$G$9/(1+$C48)^3.5+$H$9/(1+$C48)^4.5+($H$9*(1+E$42)/($C48-E$42))/(1+$C48)^4.5+Assumptions!$C$32)/Assumptions!$C$31 -> 7.6171169 | F48: =($D$9/(1+$C48)^0.6+$E$9/(1+$C48)^1.5+$F$9/(1+$C48)^2.5+$G$9/(1+$C48)^3.5+$H$9/(1+$C48)^4.5+($H$9*(1+F$42)/($C48-F$42))/(1+$C48)^4.5+Assumptions!$C$32)/Assumptions!$C$31 -> 7.7480714 | G48: =($D$9/(1+$C48)^0.6+$E$9/(1+$C48)^1.5+$F$9/(1+$C48)^2.5+$G$9/(1+$C48)^3.5+$H$9/(1+$C48)^4.5+($H$9*(1+G$42)/($C48-G$42))/(1+$C48)^4.5+Assumptions!$C$32)/Assumptions!$C$31 -> 7.9206933 | H48: =($D$9/(1+$C48)^0.6+$E$9/(1+$C48)^1.5+$F$9/(1+$C48)^2.5+$G$9/(1+$C48)^3.5+$H$9/(1+$C48)^4.5+($H$9*(1+H$42)/($C48-H$42))/(1+$C48)^4.5+Assumptions!$C$32)/Assumptions!$C$31 -> 8.1041041 | I48: =($D$9/(1+$C48)^0.6+$E$9/(1+$C48)^1.5+$F$9/(1+$C48)^2.5+$G$9/(1+$C48)^3.5+$H$9/(1+$C48)^4.5+($H$9*(1+I$42)/($C48-I$42))/(1+$C48)^4.5+Assumptions!$C$32)/Assumptions!$C$31 -> 8.2993478 | J48: =($D$9/(1+$C48)^0.6+$E$9/(1+$C48)^1.5+$F$9/(1+$C48)^2.5+$G$9/(1+$C48)^3.5+$H$9/(1+$C48)^4.5+($H$9*(1+J$42)/($C48-J$42))/(1+$C48)^4.5+Assumptions!$C$32)/Assumptions!$C$31 -> 8.5076078
C49: 0.11 | D49: =($D$9/(1+$C49)^0.6+$E$9/(1+$C49)^1.5+$F$9/(1+$C49)^2.5+$G$9/(1+$C49)^3.5+$H$9/(1+$C49)^4.5+($H$9*(1+D$42)/($C49-D$42))/(1+$C49)^4.5+Assumptions!$C$32)/Assumptions!$C$31 -> 7.0516329 | E49: =($D$9/(1+$C49)^0.6+$E$9/(1+$C49)^1.5+$F$9/(1+$C49)^2.5+$G$9/(1+$C49)^3.5+$H$9/(1+$C49)^4.5+($H$9*(1+E$42)/($C49-E$42))/(1+$C49)^4.5+Assumptions!$C$32)/Assumptions!$C$31 -> 7.2152302 | F49: =($D$9/(1+$C49)^0.6+$E$9/(1+$C49)^1.5+$F$9/(1+$C49)^2.5+$G$9/(1+$C49)^3.5+$H$9/(1+$C49)^4.5+($H$9*(1+F$42)/($C49-F$42))/(1+$C49)^4.5+Assumptions!$C$32)/Assumptions!$C$31 -> 7.3303543 | G49: =($D$9/(1+$C49)^0.6+$E$9/(1+$C49)^1.5+$F$9/(1+$C49)^2.5+$G$9/(1+$C49)^3.5+$H$9/(1+$C49)^4.5+($H$9*(1+G$42)/($C49-G$42))/(1+$C49)^4.5+Assumptions!$C$32)/Assumptions!$C$31 -> 7.4816601 | H49: =($D$9/(1+$C49)^0.6+$E$9/(1+$C49)^1.5+$F$9/(1+$C49)^2.5+$G$9/(1+$C49)^3.5+$H$9/(1+$C49)^4.5+($H$9*(1+H$42)/($C49-H$42))/(1+$C49)^4.5+Assumptions!$C$32)/Assumptions!$C$31 -> 7.6418664 | I49: =($D$9/(1+$C49)^0.6+$E$9/(1+$C49)^1.5+$F$9/(1+$C49)^2.5+$G$9/(1+$C49)^3.5+$H$9/(1+$C49)^4.5+($H$9*(1+I$42)/($C49-I$42))/(1+$C49)^4.5+Assumptions!$C$32)/Assumptions!$C$31 -> 7.811782 | J49: =($D$9/(1+$C49)^0.6+$E$9/(1+$C49)^1.5+$F$9/(1+$C49)^2.5+$G$9/(1+$C49)^3.5+$H$9/(1+$C49)^4.5+($H$9*(1+J$42)/($C49-J$42))/(1+$C49)^4.5+Assumptions!$C$32)/Assumptions!$C$31 -> 7.9923175
B52: Notes
B53: (1) Base case highlighted yellow: WACC 9.5%, g 2.25%. (2) FCF stream linked from Assumptions tab. (3) Mid-year discount convention applied.
